minici/__init__.py
minici/executors.py
minici/observers.py
minici-1.0.0.data/scripts/minici
minici-1.0.0.dist-info/LICENSE
minici-1.0.0.dist-info/METADATA
minici-1.0.0.dist-info/WHEEL
minici-1.0.0.dist-info/top_level.txt
minici-1.0.0.dist-info/RECORD
