Metadata-Version: 2.1
Name: minici
Version: 1.0.0
Summary: A tool that executes commands whenever selected files change.
Home-page: https://gitlab.com/AnthonyZimmermann/minici
Author: Anthony Zimmermann
Author-email: anthony.zimmermann@protonmail.com
License: BSD-3-Clause
Platform: UNKNOWN
License-File: LICENSE
Requires-Dist: asyncinotify
